{
  "queryCost": 1,
  "latitude": 33.874314,
  "longitude": -117.9637,
  "resolvedAddress": "92833, USA",
  "address": "92833",
  "timezone": "America/Los_Angeles",
  "tzoffset": -8.0,
  "days": [
    {
      "datetime": "2025-12-11",
      "datetimeEpoch": 1765440000,
      "tempmax": 76.7,
      "tempmin": 56.6,
      "temp": 64.4,
      "feelslikemax": 76.7,
      "feelslikemin": 56.6,
      "feelslike": 64.4,
      "dew": 46.9,
      "humidity": 54.3,
      "precip": 0.0,
      "precipprob": 0.0,
      "precipcover": 0.0,
      "preciptype": null,
      "snow": 0.0,
      "snowdepth": 0.0,
      "windgust": 7.8,
      "windspeed": 3.6,
      "winddir": 129.5,
      "pressure": 1014.7,
      "cloudcover": 6.0,
      "visibility": 13.9,
      "solarradiation": 141.0,
      "solarenergy": 12.2,
      "uvindex": 5.0,
      "severerisk": 10.0,
      "sunrise": "06:47:17",
      "sunriseEpoch": 1765464437,
      "sunset": "16:43:29",
      "sunsetEpoch": 1765500209,
      "moonphase": 0.75,
      "conditions": "Clear",
      "description": "Clear conditions throughout the day.",
      "icon": "clear-day",
      "stations": null,
      "source": "fcst",
      "hours": [
        {
          "datetime": "00:00:00",
          "datetimeEpoch": 1765440000,
          "temp": 59.1,
          "feelslike": 59.1,
          "humidity": 58.4,
          "dew": 44.5,
          "precip": 0.0,
          "precipprob": 0.0,
          "snow": 0.0,
          "snowdepth": 0.0,
          "preciptype": null,
          "windgust": 5.4,
          "windspeed": 1.8,
          "winddir": 60.0,
          "pressure": 1015.0,
          "visibility": 8.6,
          "cloudcover": 6.7,
          "solarradiation": 1.0,
          "solarenergy": 0.0,
          "uvindex": 0.0,
          "severerisk": 10.0,
          "conditions": "Clear",
          "icon": "clear-night",
          "stations": null,
          "source": "fcst"
        },
        {
          "datetime": "01:00:00",
          "datetimeEpoch": 1765443600,
          "temp": 58.2,
          "feelslike": 58.2,
          "humidity": 58.28,
          "dew": 43.6,
          "precip": 0.0,
          "precipprob": 0.0,
          "snow": 0.0,
          "snowdepth": 0.0,
          "preciptype": null,
          "windgust": 5.4,
          "windspeed": 1.8,
          "winddir": 60.0,
          "pressure": 1015.0,
          "visibility": 8.5,
          "cloudcover": 8.0,
          "solarradiation": 0.0,
          "solarenergy": 0.0,
          "uvindex": 0.0,
          "severerisk": 10.0,
          "conditions": "Clear",
          "icon": "clear-night",
          "stations": null,
          "source": "fcst"
        },
        {
          "datetime": "02:00:00",
          "datetimeEpoch": 1765447200,
          "temp": 57.6,
          "feelslike": 57.6,
          "humidity": 59.42,
          "dew": 43.6,
          "precip": 0.0,
          "precipprob": 0.0,
          "snow": 0.0,
          "snowdepth": 0.0,
          "preciptype": null,
          "windgust": 5.6,
          "windspeed": 2.0,
          "winddir": 60.0,
          "pressure": 1015.0,
          "visibility": 8.4,
          "cloudcover": 8.7,
          "solarradiation": 0.0,
          "solarenergy": 0.0,
          "uvindex": 0.0,
          "severerisk": 10.0,
          "conditions": "Clear",
          "icon": "clear-night",
          "stations": null,
          "source": "fcst"
        },
        {
          "datetime": "03:00:00",
          "datetimeEpoch": 1765450800,
          "temp": 57.1,
          "feelslike": 57.1,
          "humidity": 60.17,
          "dew": 43.4,
          "precip": 0.0,
          "precipprob": 0.0,
          "snow": 0.0,
          "snowdepth": 0.0,
          "preciptype": null,
          "windgust": 5.8,
          "windspeed": 2.5,
          "winddir": 60.0,
          "pressure": 1015.0,
          "visibility": 8.4,
          "cloudcover": 9.3,
          "solarradiation": 0.0,
          "solarenergy": 0.0,
          "uvindex": 0.0,
          "severerisk": 10.0,
          "conditions": "Clear",
          "icon": "clear-night",
          "stations": null,
          "source": "fcst"
        },
        {
          "datetime": "04:00:00",
          "datetimeEpoch": 1765454400,
          "temp": 56.6,
          "feelslike": 56.6,
          "humidity": 61.36,
          "dew": 43.4,
          "precip": 0.0,
          "precipprob": 0.0,
          "snow": 0.0,
          "snowdepth": 0.0,
          "preciptype": null,
          "windgust": 6.0,
          "windspeed": 2.7,
          "winddir": 60.0,
          "pressure": 1014.0,
          "visibility": 15.0,
          "cloudcover": 10.0,
          "solarradiation": 0.0,
          "solarenergy": 0.0,
          "uvindex": 0.0,
          "severerisk": 10.0,
          "conditions": "Clear",
          "icon": "clear-night",
          "stations": null,
          "source": "fcst"
        },
        {
          "datetime": "05:00:00",
          "datetimeEpoch": 1765458000,
          "temp": 56.6,
          "feelslike": 56.6,
          "humidity": 60.93,
          "dew": 43.2,
          "precip": 0.0,
          "precipprob": 0.0,
          "snow": 0.0,
          "snowdepth": 0.0,
          "preciptype": null,
          "windgust": 5.8,
          "windspeed": 2.5,
          "winddir": 60.0,
          "pressure": 1015.0,
          "visibility": 15.0,
          "cloudcover": 11.0,
          "solarradiation": 0.0,
          "solarenergy": 0.0,
          "uvindex": 0.0,
          "severerisk": 10.0,
          "conditions": "Clear",
          "icon": "clear-night",
          "stations": null,
          "source": "fcst"
        },
        {
          "datetime": "06:00:00",
          "datetimeEpoch": 1765461600,
          "temp": 56.6,
          "feelslike": 56.6,
          "humidity": 60.52,
          "dew": 43.1,
          "precip": 0.0,
          "precipprob": 0.0,
          "snow": 0.0,
          "snowdepth": 0.0,
          "preciptype": null,
          "windgust": 5.6,
          "windspeed": 2.0,
          "winddir": 60.0,
          "pressure": 1015.0,
          "visibility": 15.0,
          "cloudcover": 12.0,
          "solarradiation": 0.0,
          "solarenergy": 0.0,
          "uvindex": 0.0,
          "severerisk": 10.0,
          "conditions": "Clear",
          "icon": "clear-night",
          "stations": null,
          "source": "fcst"
        },
        {
          "datetime": "07:00:00",
          "datetimeEpoch": 1765465200,
          "temp": 56.6,
          "feelslike": 56.6,
          "humidity": 60.1,
          "dew": 42.9,
          "precip": 0.0,
          "precipprob": 0.0,
          "snow": 0.0,
          "snowdepth": 0.0,
          "preciptype": null,
          "windgust": 5.4,
          "windspeed": 1.8,
          "winddir": 60.0,
          "pressure": 1016.0,
          "visibility": 15.0,
          "cloudcover": 13.0,
          "solarradiation": 0.0,
          "solarenergy": 0.0,
          "uvindex": 0.0,
          "severerisk": 10.0,
          "conditions": "Clear",
          "icon": "clear-day",
          "stations": null,
          "source": "fcst"
        },
        {
          "datetime": "08:00:00",
          "datetimeEpoch": 1765468800,
          "temp": 60.5,
          "feelslike": 60.5,
          "humidity": 54.73,
          "dew": 44.1,
          "precip": 0.0,
          "precipprob": 0.0,
          "snow": 0.0,
          "snowdepth": 0.0,
          "preciptype": null,
          "windgust": 4.7,
          "windspeed": 1.6,
          "winddir": 63.3,
          "pressure": 1016.0,
          "visibility": 15.0,
          "cloudcover": 10.0,
          "solarradiation": 42.0,
          "solarenergy": 0.2,
          "uvindex": 0.0,
          "severerisk": 10.0,
          "conditions": "Clear",
          "icon": "clear-day",
          "stations": null,
          "source": "fcst"
        },
        {
          "datetime": "09:00:00",
          "datetimeEpoch": 1765472400,
          "temp": 64.7,
          "feelslike": 64.7,
          "humidity": 49.97,
          "dew": 45.6,
          "precip": 0.0,
          "precipprob": 0.0,
          "snow": 0.0,
          "snowdepth": 0.0,
          "preciptype": null,
          "windgust": 4.0,
          "windspeed": 1.1,
          "winddir": 66.7,
          "pressure": 1016.0,
          "visibility": 15.0,
          "cloudcover": 7.0,
          "solarradiation": 85.0,
          "solarenergy": 0.3,
          "uvindex": 1.0,
          "severerisk": 10.0,
          "conditions": "Clear",
          "icon": "clear-day",
          "stations": null,
          "source": "fcst"
        },
        {
          "datetime": "10:00:00",
          "datetimeEpoch": 1765476000,
          "temp": 68.6,
          "feelslike": 68.6,
          "humidity": 45.7,
          "dew": 46.8,
          "precip": 0.0,
          "precipprob": 0.0,
          "snow": 0.0,
          "snowdepth": 0.0,
          "preciptype": null,
          "windgust": 3.4,
          "windspeed": 0.9,
          "winddir": 70.0,
          "pressure": 1016.0,
          "visibility": 15.0,
          "cloudcover": 4.0,
          "solarradiation": 127.0,
          "solarenergy": 0.5,
          "uvindex": 1.0,
          "severerisk": 10.0,
          "conditions": "Clear",
          "icon": "clear-day",
          "stations": null,
          "source": "fcst"
        },
        {
          "datetime": "11:00:00",
          "datetimeEpoch": 1765479600,
          "temp": 71.3,
          "feelslike": 71.3,
          "humidity": 41.68,
          "dew": 46.8,
          "precip": 0.0,
          "precipprob": 0.0,
          "snow": 0.0,
          "snowdepth": 0.0,
          "preciptype": null,
          "windgust": 4.7,
          "windspeed": 1.6,
          "winddir": 126.7,
          "pressure": 1016.0,
          "visibility": 15.0,
          "cloudcover": 3.3,
          "solarradiation": 268.0,
          "solarenergy": 1.0,
          "uvindex": 3.0,
          "severerisk": 10.0,
          "conditions": "Clear",
          "icon": "clear-day",
          "stations": null,
          "source": "fcst"
        },
        {
          "datetime": "12:00:00",
          "datetimeEpoch": 1765483200,
          "temp": 74.0,
          "feelslike": 74.0,
          "humidity": 38.31,
          "dew": 47.0,
          "precip": 0.0,
          "precipprob": 0.0,
          "snow": 0.0,
          "snowdepth": 0.0,
          "preciptype": null,
          "windgust": 6.3,
          "windspeed": 2.0,
          "winddir": 183.3,
          "pressure": 1015.0,
          "visibility": 15.0,
          "cloudcover": 2.7,
          "solarradiation": 408.0,
          "solarenergy": 1.5,
          "uvindex": 4.0,
          "severerisk": 10.0,
          "conditions": "Clear",
          "icon": "clear-day",
          "stations": null,
          "source": "fcst"
        },
        {
          "datetime": "13:00:00",
          "datetimeEpoch": 1765486800,
          "temp": 76.7,
          "feelslike": 76.7,
          "humidity": 35.01,
          "dew": 47.0,
          "precip": 0.0,
          "precipprob": 0.0,
          "snow": 0.0,
          "snowdepth": 0.0,
          "preciptype": null,
          "windgust": 7.6,
          "windspeed": 2.7,
          "winddir": 240.0,
          "pressure": 1014.0,
          "visibility": 15.0,
          "cloudcover": 2.0,
          "solarradiation": 549.0,
          "solarenergy": 2.0,
          "uvindex": 5.0,
          "severerisk": 10.0,
          "conditions": "Clear",
          "icon": "clear-day",
          "stations": null,
          "source": "fcst"
        },
        {
          "datetime": "14:00:00",
          "datetimeEpoch": 1765490400,
          "temp": 75.8,
          "feelslike": 75.8,
          "humidity": 37.82,
          "dew": 48.3,
          "precip": 0.0,
          "precipprob": 0.0,
          "snow": 0.0,
          "snowdepth": 0.0,
          "preciptype": null,
          "windgust": 7.6,
          "windspeed": 2.9,
          "winddir": 236.7,
          "pressure": 1014.0,
          "visibility": 15.0,
          "cloudcover": 2.0,
          "solarradiation": 513.0,
          "solarenergy": 1.8,
          "uvindex": 5.0,
          "severerisk": 10.0,
          "conditions": "Clear",
          "icon": "clear-day",
          "stations": null,
          "source": "fcst"
        },
        {
          "datetime": "15:00:00",
          "datetimeEpoch": 1765494000,
          "temp": 74.9,
          "feelslike": 74.9,
          "humidity": 40.58,
          "dew": 49.4,
          "precip": 0.0,
          "precipprob": 0.0,
          "snow": 0.0,
          "snowdepth": 0.0,
          "preciptype": null,
          "windgust": 7.8,
          "windspeed": 3.4,
          "winddir": 233.3,
          "pressure": 1014.0,
          "visibility": 15.0,
          "cloudcover": 2.0,
          "solarradiation": 477.0,
          "solarenergy": 1.7,
          "uvindex": 5.0,
          "severerisk": 10.0,
          "conditions": "Clear",
          "icon": "clear-day",
          "stations": null,
          "source": "fcst"
        },
        {
          "datetime": "16:00:00",
          "datetimeEpoch": 1765497600,
          "temp": 74.0,
          "feelslike": 74.0,
          "humidity": 43.82,
          "dew": 50.6,
          "precip": 0.0,
          "precipprob": 0.0,
          "snow": 0.0,
          "snowdepth": 0.0,
          "preciptype": null,
          "windgust": 7.8,
          "windspeed": 3.6,
          "winddir": 230.0,
          "pressure": 1014.0,
          "visibility": 15.0,
          "cloudcover": 2.0,
          "solarradiation": 441.0,
          "solarenergy": 1.6,
          "uvindex": 4.0,
          "severerisk": 10.0,
          "conditions": "Clear",
          "icon": "clear-day",
          "stations": null,
          "source": "fcst"
        },
        {
          "datetime": "17:00:00",
          "datetimeEpoch": 1765501200,
          "temp": 70.8,
          "feelslike": 70.8,
          "humidity": 49.55,
          "dew": 51.0,
          "precip": 0.0,
          "precipprob": 0.0,
          "snow": 0.0,
          "snowdepth": 0.0,
          "preciptype": null,
          "windgust": 6.0,
          "windspeed": 2.7,
          "winddir": 230.0,
          "pressure": 1014.0,
          "visibility": 15.0,
          "cloudcover": 2.3,
          "solarradiation": 296.0,
          "solarenergy": 1.1,
          "uvindex": 0.0,
          "severerisk": 10.0,
          "conditions": "Clear",
          "icon": "clear-night",
          "stations": null,
          "source": "fcst"
        },
        {
          "datetime": "18:00:00",
          "datetimeEpoch": 1765504800,
          "temp": 67.4,
          "feelslike": 67.4,
          "humidity": 56.45,
          "dew": 51.3,
          "precip": 0.0,
          "precipprob": 0.0,
          "snow": 0.0,
          "snowdepth": 0.0,
          "preciptype": null,
          "windgust": 4.3,
          "windspeed": 1.8,
          "winddir": 230.0,
          "pressure": 1014.0,
          "visibility": 15.0,
          "cloudcover": 2.7,
          "solarradiation": 152.0,
          "solarenergy": 0.5,
          "uvindex": 0.0,
          "severerisk": 10.0,
          "conditions": "Clear",
          "icon": "clear-night",
          "stations": null,
          "source": "fcst"
        },
        {
          "datetime": "19:00:00",
          "datetimeEpoch": 1765508400,
          "temp": 64.1,
          "feelslike": 64.1,
          "humidity": 64.02,
          "dew": 51.7,
          "precip": 0.0,
          "precipprob": 0.0,
          "snow": 0.0,
          "snowdepth": 0.0,
          "preciptype": null,
          "windgust": 2.5,
          "windspeed": 0.9,
          "winddir": 230.0,
          "pressure": 1014.0,
          "visibility": 15.0,
          "cloudcover": 3.0,
          "solarradiation": 7.0,
          "solarenergy": 0.0,
          "uvindex": 0.0,
          "severerisk": 10.0,
          "conditions": "Clear",
          "icon": "clear-night",
          "stations": null,
          "source": "fcst"
        },
        {
          "datetime": "20:00:00",
          "datetimeEpoch": 1765512000,
          "temp": 62.9,
          "feelslike": 62.9,
          "humidity": 65.15,
          "dew": 51.0,
          "precip": 0.0,
          "precipprob": 0.0,
          "snow": 0.0,
          "snowdepth": 0.0,
          "preciptype": null,
          "windgust": 2.7,
          "windspeed": 0.9,
          "winddir": 190.0,
          "pressure": 1014.0,
          "visibility": 15.0,
          "cloudcover": 3.7,
          "solarradiation": 6.0,
          "solarenergy": 0.0,
          "uvindex": 0.0,
          "severerisk": 10.0,
          "conditions": "Clear",
          "icon": "clear-night",
          "stations": null,
          "source": "fcst"
        },
        {
          "datetime": "21:00:00",
          "datetimeEpoch": 1765515600,
          "temp": 61.4,
          "feelslike": 61.4,
          "humidity": 66.29,
          "dew": 50.1,
          "precip": 0.0,
          "precipprob": 0.0,
          "snow": 0.0,
          "snowdepth": 0.0,
          "preciptype": null,
          "windgust": 3.1,
          "windspeed": 0.9,
          "winddir": 150.0,
          "pressure": 1014.0,
          "visibility": 15.0,
          "cloudcover": 4.3,
          "solarradiation": 5.0,
          "solarenergy": 0.0,
          "uvindex": 0.0,
          "severerisk": 10.0,
          "conditions": "Clear",
          "icon": "clear-night",
          "stations": null,
          "source": "fcst"
        },
        {
          "datetime": "22:00:00",
          "datetimeEpoch": 1765519200,
          "temp": 60.2,
          "feelslike": 60.2,
          "humidity": 67.49,
          "dew": 49.4,
          "precip": 0.0,
          "precipprob": 0.0,
          "snow": 0.0,
          "snowdepth": 0.0,
          "preciptype": null,
          "windgust": 3.4,
          "windspeed": 0.9,
          "winddir": 110.0,
          "pressure": 1014.0,
          "visibility": 15.0,
          "cloudcover": 5.0,
          "solarradiation": 4.0,
          "solarenergy": 0.0,
          "uvindex": 0.0,
          "severerisk": 10.0,
          "conditions": "Clear",
          "icon": "clear-night",
          "stations": null,
          "source": "fcst"
        },
        {
          "datetime": "23:00:00",
          "datetimeEpoch": 1765522800,
          "temp": 59.1,
          "feelslike": 59.1,
          "humidity": 68.28,
          "dew": 48.6,
          "precip": 0.0,
          "precipprob": 0.0,
          "snow": 0.0,
          "snowdepth": 0.0,
          "preciptype": null,
          "windgust": 3.6,
          "windspeed": 1.1,
          "winddir": 100.0,
          "pressure": 1014.0,
          "visibility": 15.0,
          "cloudcover": 8.3,
          "solarradiation": 3.0,
          "solarenergy": 0.0,
          "uvindex": 0.0,
          "severerisk": 10.0,
          "conditions": "Clear",
          "icon": "clear-night",
          "stations": null,
          "source": "fcst"
        }
      ]
    },
    {
      "datetime": "2025-12-12",
      "datetimeEpoch": 1765526400,
      "tempmax": 73.7,
      "tempmin": 54.8,
      "temp": 62.4,
      "feelslikemax": 73.7,
      "feelslikemin": 54.8,
      "feelslike": 62.4,
      "dew": 49.9,
      "humidity": 65.0,
      "precip": 0.213,
      "precipprob": 0.0,
      "precipcover": 4.17,
      "preciptype": [
        "rain"
      ],
      "snow": 0.0,
      "snowdepth": 0.0,
      "windgust": 8.3,
      "windspeed": 3.6,
      "winddir": 171.1,
      "pressure": 1014.4,
      "cloudcover": 15.9,
      "visibility": 15.0,
      "solarradiation": 120.5,
      "solarenergy": 10.4,
      "uvindex": 5.0,
      "severerisk": 10.0,
      "sunrise": "06:47:59",
      "sunriseEpoch": 1765550879,
      "sunset": "16:43:44",
      "sunsetEpoch": 1765586624,
      "moonphase": 0.76,
      "conditions": "Clear",
      "description": "Clear conditions throughout the day.",
      "icon": "clear-day",
      "stations": null,
      "source": "fcst",
      "hours": [
        {
          "datetime": "00:00:00",
          "datetimeEpoch": 1765526400,
          "temp": 58.0,
          "feelslike": 58.0,
          "humidity": 69.08,
          "dew": 47.9,
          "precip": 0.0,
          "precipprob": 0.0,
          "snow": 0.0,
          "snowdepth": 0.0,
          "preciptype": null,
          "windgust": 4.0,
          "windspeed": 1.6,
          "winddir": 90.0,
          "pressure": 1014.0,
          "visibility": 15.0,
          "cloudcover": 11.7,
          "solarradiation": 1.0,
          "solarenergy": 0.0,
          "uvindex": 0.0,
          "severerisk": 10.0,
          "conditions": "Clear",
          "icon": "clear-night",
          "stations": null,
          "source": "fcst"
        },
        {
          "datetime": "01:00:00",
          "datetimeEpoch": 1765530000,
          "temp": 56.9,
          "feelslike": 56.9,
          "humidity": 69.9,
          "dew": 47.2,
          "precip": 0.0,
          "precipprob": 0.0,
          "snow": 0.0,
          "snowdepth": 0.0,
          "preciptype": null,
          "windgust": 4.3,
          "windspeed": 1.8,
          "winddir": 80.0,
          "pressure": 1014.0,
          "visibility": 15.0,
          "cloudcover": 15.0,
          "solarradiation": 0.0,
          "solarenergy": 0.0,
          "uvindex": 0.0,
          "severerisk": 10.0,
          "conditions": "Clear",
          "icon": "clear-night",
          "stations": null,
          "source": "fcst"
        },
        {
          "datetime": "02:00:00",
          "datetimeEpoch": 1765533600,
          "temp": 56.2,
          "feelslike": 56.2,
          "humidity": 71.26,
          "dew": 47.0,
          "precip": 0.0,
          "precipprob": 0.0,
          "snow": 0.0,
          "snowdepth": 0.0,
          "preciptype": null,
          "windgust": 4.5,
          "windspeed": 1.8,
          "winddir": 80.0,
          "pressure": 1014.0,
          "visibility": 15.0,
          "cloudcover": 17.0,
          "solarradiation": 0.0,
          "solarenergy": 0.0,
          "uvindex": 0.0,
          "severerisk": 10.0,
          "conditions": "Clear",
          "icon": "clear-night",
          "stations": null,
          "source": "fcst"
        },
        {
          "datetime": "03:00:00",
          "datetimeEpoch": 1765537200,
          "temp": 55.7,
          "feelslike": 55.7,
          "humidity": 72.18,
          "dew": 46.8,
          "precip": 0.0,
          "precipprob": 0.0,
          "snow": 0.0,
          "snowdepth": 0.0,
          "preciptype": null,
          "windgust": 4.7,
          "windspeed": 1.8,
          "winddir": 80.0,
          "pressure": 1014.0,
          "visibility": 15.0,
          "cloudcover": 19.0,
          "solarradiation": 0.0,
          "solarenergy": 0.0,
          "uvindex": 0.0,
          "severerisk": 10.0,
          "conditions": "Clear",
          "icon": "clear-night",
          "stations": null,
          "source": "fcst"
        },
        {
          "datetime": "04:00:00",
          "datetimeEpoch": 1765540800,
          "temp": 54.9,
          "feelslike": 54.9,
          "humidity": 73.59,
          "dew": 46.7,
          "precip": 0.0,
          "precipprob": 0.0,
          "snow": 0.0,
          "snowdepth": 0.0,
          "preciptype": null,
          "windgust": 4.9,
          "windspeed": 1.8,
          "winddir": 80.0,
          "pressure": 1014.0,
          "visibility": 15.0,
          "cloudcover": 21.0,
          "solarradiation": 0.0,
          "solarenergy": 0.0,
          "uvindex": 0.0,
          "severerisk": 10.0,
          "conditions": "Partially cloudy",
          "icon": "partly-cloudy-night",
          "stations": null,
          "source": "fcst"
        },
        {
          "datetime": "05:00:00",
          "datetimeEpoch": 1765544400,
          "temp": 54.9,
          "feelslike": 54.9,
          "humidity": 73.09,
          "dew": 46.5,
          "precip": 0.0,
          "precipprob": 0.0,
          "snow": 0.0,
          "snowdepth": 0.0,
          "preciptype": null,
          "windgust": 4.7,
          "windspeed": 1.8,
          "winddir": 76.7,
          "pressure": 1014.0,
          "visibility": 15.0,
          "cloudcover": 22.7,
          "solarradiation": 0.0,
          "solarenergy": 0.0,
          "uvindex": 0.0,
          "severerisk": 10.0,
          "conditions": "Partially cloudy",
          "icon": "partly-cloudy-night",
          "stations": null,
          "source": "fcst"
        },
        {
          "datetime": "06:00:00",
          "datetimeEpoch": 1765548000,
          "temp": 54.8,
          "feelslike": 54.8,
          "humidity": 73.07,
          "dew": 46.3,
          "precip": 0.0,
          "precipprob": 0.0,
          "snow": 0.0,
          "snowdepth": 0.0,
          "preciptype": null,
          "windgust": 4.5,
          "windspeed": 1.8,
          "winddir": 73.3,
          "pressure": 1015.0,
          "visibility": 15.0,
          "cloudcover": 24.3,
          "solarradiation": 0.0,
          "solarenergy": 0.0,
          "uvindex": 0.0,
          "severerisk": 10.0,
          "conditions": "Partially cloudy",
          "icon": "partly-cloudy-night",
          "stations": null,
          "source": "fcst"
        },
        {
          "datetime": "07:00:00",
          "datetimeEpoch": 1765551600,
          "temp": 54.8,
          "feelslike": 54.8,
          "humidity": 72.58,
          "dew": 46.1,
          "precip": 0.0,
          "precipprob": 0.0,
          "snow": 0.0,
          "snowdepth": 0.0,
          "preciptype": null,
          "windgust": 4.3,
          "windspeed": 1.8,
          "winddir": 70.0,
          "pressure": 1015.0,
          "visibility": 15.0,
          "cloudcover": 26.0,
          "solarradiation": 0.0,
          "solarenergy": 0.0,
          "uvindex": 0.0,
          "severerisk": 10.0,
          "conditions": "Partially cloudy",
          "icon": "partly-cloudy-day",
          "stations": null,
          "source": "fcst"
        },
        {
          "datetime": "08:00:00",
          "datetimeEpoch": 1765555200,
          "temp": 58.7,
          "feelslike": 58.7,
          "humidity": 65.53,
          "dew": 47.2,
          "precip": 0.0,
          "precipprob": 0.0,
          "snow": 0.0,
          "snowdepth": 0.0,
          "preciptype": null,
          "windgust": 3.8,
          "windspeed": 1.6,
          "winddir": 123.3,
          "pressure": 1015.0,
          "visibility": 15.0,
          "cloudcover": 20.7,
          "solarradiation": 41.0,
          "solarenergy": 0.1,
          "uvindex": 0.0,
          "severerisk": 10.0,
          "conditions": "Partially cloudy",
          "icon": "partly-cloudy-day",
          "stations": null,
          "source": "fcst"
        },
        {
          "datetime": "09:00:00",
          "datetimeEpoch": 1765558800,
          "temp": 62.5,
          "feelslike": 62.5,
          "humidity": 60.07,
          "dew": 48.5,
          "precip": 0.0,
          "precipprob": 0.0,
          "snow": 0.0,
          "snowdepth": 0.0,
          "preciptype": null,
          "windgust": 3.6,
          "windspeed": 1.1,
          "winddir": 176.7,
          "pressure": 1016.0,
          "visibility": 15.0,
          "cloudcover": 15.3,
          "solarradiation": 81.0,
          "solarenergy": 0.3,
          "uvindex": 1.0,
          "severerisk": 10.0,
          "conditions": "Clear",
          "icon": "clear-day",
          "stations": null,
          "source": "fcst"
        },
        {
          "datetime": "10:00:00",
          "datetimeEpoch": 1765562400,
          "temp": 66.5,
          "feelslike": 66.5,
          "humidity": 54.47,
          "dew": 49.5,
          "precip": 0.0,
          "precipprob": 0.0,
          "snow": 0.0,
          "snowdepth": 0.0,
          "preciptype": null,
          "windgust": 3.1,
          "windspeed": 0.9,
          "winddir": 230.0,
          "pressure": 1016.0,
          "visibility": 15.0,
          "cloudcover": 10.0,
          "solarradiation": 122.0,
          "solarenergy": 0.4,
          "uvindex": 1.0,
          "severerisk": 10.0,
          "conditions": "Clear",
          "icon": "clear-day",
          "stations": null,
          "source": "fcst"
        },
        {
          "datetime": "11:00:00",
          "datetimeEpoch": 1765566000,
          "temp": 68.8,
          "feelslike": 68.8,
          "humidity": 50.93,
          "dew": 49.9,
          "precip": 0.0,
          "precipprob": 0.0,
          "snow": 0.0,
          "snowdepth": 0.0,
          "preciptype": null,
          "windgust": 4.7,
          "windspeed": 1.6,
          "winddir": 230.0,
          "pressure": 1015.0,
          "visibility": 15.0,
          "cloudcover": 9.7,
          "solarradiation": 237.0,
          "solarenergy": 0.9,
          "uvindex": 2.0,
          "severerisk": 10.0,
          "conditions": "Clear",
          "icon": "clear-day",
          "stations": null,
          "source": "fcst"
        },
        {
          "datetime": "12:00:00",
          "datetimeEpoch": 1765569600,
          "temp": 71.3,
          "feelslike": 71.3,
          "humidity": 47.05,
          "dew": 50.1,
          "precip": 0.0,
          "precipprob": 0.0,
          "snow": 0.0,
          "snowdepth": 0.0,
          "preciptype": null,
          "windgust": 6.0,
          "windspeed": 2.0,
          "winddir": 230.0,
          "pressure": 1014.0,
          "visibility": 15.0,
          "cloudcover": 9.3,
          "solarradiation": 352.0,
          "solarenergy": 1.3,
          "uvindex": 4.0,
          "severerisk": 10.0,
          "conditions": "Clear",
          "icon": "clear-day",
          "stations": null,
          "source": "fcst"
        },
        {
          "datetime": "13:00:00",
          "datetimeEpoch": 1765573200,
          "temp": 73.7,
          "feelslike": 73.7,
          "humidity": 44.06,
          "dew": 50.4,
          "precip": 0.0,
          "precipprob": 0.0,
          "snow": 0.0,
          "snowdepth": 0.0,
          "preciptype": null,
          "windgust": 7.6,
          "windspeed": 2.7,
          "winddir": 230.0,
          "pressure": 1014.0,
          "visibility": 15.0,
          "cloudcover": 9.0,
          "solarradiation": 467.0,
          "solarenergy": 1.7,
          "uvindex": 5.0,
          "severerisk": 10.0,
          "conditions": "Clear",
          "icon": "clear-day",
          "stations": null,
          "source": "fcst"
        },
        {
          "datetime": "14:00:00",
          "datetimeEpoch": 1765576800,
          "temp": 72.9,
          "feelslike": 72.9,
          "humidity": 46.67,
          "dew": 51.3,
          "precip": 0.0,
          "precipprob": 0.0,
          "snow": 0.0,
          "snowdepth": 0.0,
          "preciptype": null,
          "windgust": 7.8,
          "windspeed": 2.9,
          "winddir": 230.0,
          "pressure": 1013.0,
          "visibility": 15.0,
          "cloudcover": 10.3,
          "solarradiation": 433.0,
          "solarenergy": 1.6,
          "uvindex": 4.0,
          "severerisk": 10.0,
          "conditions": "Clear",
          "icon": "clear-day",
          "stations": null,
          "source": "fcst"
        },
        {
          "datetime": "15:00:00",
          "datetimeEpoch": 1765580400,
          "temp": 72.2,
          "feelslike": 72.2,
          "humidity": 49.11,
          "dew": 52.1,
          "precip": 0.0,
          "precipprob": 0.0,
          "snow": 0.0,
          "snowdepth": 0.0,
          "preciptype": null,
          "windgust": 8.1,
          "windspeed": 3.4,
          "winddir": 230.0,
          "pressure": 1013.0,
          "visibility": 15.0,
          "cloudcover": 11.7,
          "solarradiation": 400.0,
          "solarenergy": 1.4,
          "uvindex": 4.0,
          "severerisk": 10.0,
          "conditions": "Clear",
          "icon": "clear-day",
          "stations": null,
          "source": "fcst"
        },
        {
          "datetime": "16:00:00",
          "datetimeEpoch": 1765584000,
          "temp": 71.5,
          "feelslike": 71.5,
          "humidity": 52.01,
          "dew": 53.0,
          "precip": 0.0,
          "precipprob": 0.0,
          "snow": 0.0,
          "snowdepth": 0.0,
          "preciptype": null,
          "windgust": 8.3,
          "windspeed": 3.6,
          "winddir": 230.0,
          "pressure": 1013.0,
          "visibility": 15.0,
          "cloudcover": 13.0,
          "solarradiation": 366.0,
          "solarenergy": 1.3,
          "uvindex": 4.0,
          "severerisk": 10.0,
          "conditions": "Clear",
          "icon": "clear-day",
          "stations": null,
          "source": "fcst"
        },
        {
          "datetime": "17:00:00",
          "datetimeEpoch": 1765587600,
          "temp": 68.3,
          "feelslike": 68.3,
          "humidity": 58.47,
          "dew": 53.1,
          "precip": 0.0,
          "precipprob": 0.0,
          "snow": 0.0,
          "snowdepth": 0.0,
          "preciptype": null,
          "windgust": 6.5,
          "windspeed": 2.7,
          "winddir": 226.7,
          "pressure": 1013.0,
          "visibility": 15.0,
          "cloudcover": 13.7,
          "solarradiation": 246.0,
          "solarenergy": 0.9,
          "uvindex": 0.0,
          "severerisk": 10.0,
          "conditions": "Clear",
          "icon": "clear-night",
          "stations": null,
          "source": "fcst"
        },
        {
          "datetime": "18:00:00",
          "datetimeEpoch": 1765591200,
          "temp": 65.2,
          "feelslike": 65.2,
          "humidity": 65.43,
          "dew": 53.3,
          "precip": 0.0,
          "precipprob": 0.0,
          "snow": 0.0,
          "snowdepth": 0.0,
          "preciptype": null,
          "windgust": 4.9,
          "windspeed": 1.8,
          "winddir": 223.3,
          "pressure": 1014.0,
          "visibility": 15.0,
          "cloudcover": 14.3,
          "solarradiation": 126.0,
          "solarenergy": 0.5,
          "uvindex": 0.0,
          "severerisk": 10.0,
          "conditions": "Clear",
          "icon": "clear-night",
          "stations": null,
          "source": "fcst"
        },
        {
          "datetime": "19:00:00",
          "datetimeEpoch": 1765594800,
          "temp": 62.0,
          "feelslike": 62.0,
          "humidity": 73.78,
          "dew": 53.5,
          "precip": 0.0,
          "precipprob": 0.0,
          "snow": 0.0,
          "snowdepth": 0.0,
          "preciptype": null,
          "windgust": 3.1,
          "windspeed": 0.9,
          "winddir": 220.0,
          "pressure": 1015.0,
          "visibility": 15.0,
          "cloudcover": 15.0,
          "solarradiation": 6.0,
          "solarenergy": 0.0,
          "uvindex": 0.0,
          "severerisk": 10.0,
          "conditions": "Clear",
          "icon": "clear-night",
          "stations": null,
          "source": "fcst"
        },
        {
          "datetime": "20:00:00",
          "datetimeEpoch": 1765598400,
          "temp": 60.9,
          "feelslike": 60.9,
          "humidity": 76.15,
          "dew": 53.3,
          "precip": 0.0,
          "precipprob": 0.0,
          "snow": 0.0,
          "snowdepth": 0.0,
          "preciptype": null,
          "windgust": 3.6,
          "windspeed": 1.1,
          "winddir": 183.3,
          "pressure": 1015.0,
          "visibility": 15.0,
          "cloudcover": 16.0,
          "solarradiation": 5.0,
          "solarenergy": 0.0,
          "uvindex": 0.0,
          "severerisk": 10.0,
          "conditions": "Clear",
          "icon": "clear-night",
          "stations": null,
          "source": "fcst"
        },
        {
          "datetime": "21:00:00",
          "datetimeEpoch": 1765602000,
          "temp": 59.6,
          "feelslike": 59.6,
          "humidity": 78.6,
          "dew": 53.0,
          "precip": 0.0,
          "precipprob": 0.0,
          "snow": 0.0,
          "snowdepth": 0.0,
          "preciptype": null,
          "windgust": 3.8,
          "windspeed": 1.6,
          "winddir": 146.7,
          "pressure": 1015.0,
          "visibility": 15.0,
          "cloudcover": 17.0,
          "solarradiation": 4.0,
          "solarenergy": 0.0,
          "uvindex": 0.0,
          "severerisk": 10.0,
          "conditions": "Clear",
          "icon": "clear-night",
          "stations": null,
          "source": "fcst"
        },
        {
          "datetime": "22:00:00",
          "datetimeEpoch": 1765605600,
          "temp": 58.6,
          "feelslike": 58.6,
          "humidity": 81.15,
          "dew": 52.8,
          "precip": 0.213,
          "precipprob": 0.0,
          "snow": 0.0,
          "snowdepth": 0.0,
          "preciptype": [
            "rain"
          ],
          "windgust": 4.3,
          "windspeed": 1.8,
          "winddir": 110.0,
          "pressure": 1015.0,
          "visibility": 15.0,
          "cloudcover": 18.0,
          "solarradiation": 3.0,
          "solarenergy": 0.0,
          "uvindex": 0.0,
          "severerisk": 10.0,
          "conditions": "Clear",
          "icon": "clear-night",
          "stations": null,
          "source": "fcst"
        },
        {
          "datetime": "23:00:00",
          "datetimeEpoch": 1765609200,
          "temp": 57.8,
          "feelslike": 57.8,
          "humidity": 81.1,
          "dew": 52.1,
          "precip": 0.0,
          "precipprob": 0.0,
          "snow": 0.0,
          "snowdepth": 0.0,
          "preciptype": null,
          "windgust": 4.3,
          "windspeed": 1.8,
          "winddir": 93.3,
          "pressure": 1015.0,
          "visibility": 15.0,
          "cloudcover": 22.0,
          "solarradiation": 2.0,
          "solarenergy": 0.0,
          "uvindex": 0.0,
          "severerisk": 10.0,
          "conditions": "Partially cloudy",
          "icon": "partly-cloudy-night",
          "stations": null,
          "source": "fcst"
        }
      ]
    },
    {
      "datetime": "2025-12-13",
      "datetimeEpoch": 1765612800,
      "tempmax": 71.3,
      "tempmin": 53.7,
      "temp": 60.7,
      "feelslikemax": 71.3,
      "feelslikemin": 53.7,
      "feelslike": 60.7,
      "dew": 51.8,
      "humidity": 73.7,
      "precip": 0.016,
      "precipprob": 0.0,
      "precipcover": 4.17,
      "preciptype": [
        "rain"
      ],
      "snow": 0.0,
      "snowdepth": 0.0,
      "windgust": 9.2,
      "windspeed": 4.5,
      "winddir": 186.9,
      "pressure": 1014.8,
      "cloudcover": 36.1,
      "visibility": 15.0,
      "solarradiation": 117.0,
      "solarenergy": 9.9,
      "uvindex": 4.0,
      "severerisk": 10.0,
      "sunrise": "06:48:41",
      "sunriseEpoch": 1765637321,
      "sunset": "16:44:00",
      "sunsetEpoch": 1765673040,
      "moonphase": 0.79,
      "conditions": "Partially cloudy",
      "description": "Partly cloudy throughout the day.",
      "icon": "partly-cloudy-day",
      "stations": null,
      "source": "fcst",
      "hours": [
        {
          "datetime": "00:00:00",
          "datetimeEpoch": 1765612800,
          "temp": 57.1,
          "feelslike": 57.1,
          "humidity": 80.51,
          "dew": 51.2,
          "precip": 0.0,
          "precipprob": 0.0,
          "snow": 0.0,
          "snowdepth": 0.0,
          "preciptype": null,
          "windgust": 4.0,
          "windspeed": 1.8,
          "winddir": 76.7,
          "pressure": 1015.0,
          "visibility": 15.0,
          "cloudcover": 26.0,
          "solarradiation": 1.0,
          "solarenergy": 0.0,
          "uvindex": 0.0,
          "severerisk": 10.0,
          "conditions": "Partially cloudy",
          "icon": "partly-cloudy-night",
          "stations": null,
          "source": "fcst"
        },
        {
          "datetime": "01:00:00",
          "datetimeEpoch": 1765616400,
          "temp": 56.4,
          "feelslike": 56.4,
          "humidity": 80.45,
          "dew": 50.4,
          "precip": 0.0,
          "precipprob": 0.0,
          "snow": 0.0,
          "snowdepth": 0.0,
          "preciptype": null,
          "windgust": 4.0,
          "windspeed": 1.8,
          "winddir": 60.0,
          "pressure": 1015.0,
          "visibility": 15.0,
          "cloudcover": 30.0,
          "solarradiation": 0.0,
          "solarenergy": 0.0,
          "uvindex": 0.0,
          "severerisk": 10.0,
          "conditions": "Partially cloudy",
          "icon": "partly-cloudy-night",
          "stations": null,
          "source": "fcst"
        },
        {
          "datetime": "02:00:00",
          "datetimeEpoch": 1765620000,
          "temp": 55.7,
          "feelslike": 55.7,
          "humidity": 81.48,
          "dew": 50.1,
          "precip": 0.0,
          "precipprob": 0.0,
          "snow": 0.0,
          "snowdepth": 0.0,
          "preciptype": null,
          "windgust": 4.3,
          "windspeed": 1.8,
          "winddir": 60.0,
          "pressure": 1015.0,
          "visibility": 15.0,
          "cloudcover": 34.7,
          "solarradiation": 0.0,
          "solarenergy": 0.0,
          "uvindex": 0.0,
          "severerisk": 10.0,
          "conditions": "Partially cloudy",
          "icon": "partly-cloudy-night",
          "stations": null,
          "source": "fcst"
        },
        {
          "datetime": "03:00:00",
          "datetimeEpoch": 1765623600,
          "temp": 55.1,
          "feelslike": 55.1,
          "humidity": 81.99,
          "dew": 49.7,
          "precip": 0.0,
          "precipprob": 0.0,
          "snow": 0.0,
          "snowdepth": 0.0,
          "preciptype": null,
          "windgust": 4.7,
          "windspeed": 1.8,
          "winddir": 60.0,
          "pressure": 1014.0,
          "visibility": 15.0,
          "cloudcover": 39.3,
          "solarradiation": 0.0,
          "solarenergy": 0.0,
          "uvindex": 0.0,
          "severerisk": 10.0,
          "conditions": "Partially cloudy",
          "icon": "partly-cloudy-night",
          "stations": null,
          "source": "fcst"
        },
        {
          "datetime": "04:00:00",
          "datetimeEpoch": 1765627200,
          "temp": 54.4,
          "feelslike": 54.4,
          "humidity": 83.05,
          "dew": 49.4,
          "precip": 0.016,
          "precipprob": 0.0,
          "snow": 0.0,
          "snowdepth": 0.0,
          "preciptype": [
            "rain"
          ],
          "windgust": 4.9,
          "windspeed": 1.8,
          "winddir": 60.0,
          "pressure": 1014.0,
          "visibility": 15.0,
          "cloudcover": 44.0,
          "solarradiation": 0.0,
          "solarenergy": 0.0,
          "uvindex": 0.0,
          "severerisk": 10.0,
          "conditions": "Partially cloudy",
          "icon": "partly-cloudy-night",
          "stations": null,
          "source": "fcst"
        },
        {
          "datetime": "05:00:00",
          "datetimeEpoch": 1765630800,
          "temp": 54.2,
          "feelslike": 54.2,
          "humidity": 83.59,
          "dew": 49.4,
          "precip": 0.0,
          "precipprob": 0.0,
          "snow": 0.0,
          "snowdepth": 0.0,
          "preciptype": null,
          "windgust": 4.7,
          "windspeed": 1.8,
          "winddir": 60.0,
          "pressure": 1014.0,
          "visibility": 15.0,
          "cloudcover": 47.0,
          "solarradiation": 0.0,
          "solarenergy": 0.0,
          "uvindex": 0.0,
          "severerisk": 10.0,
          "conditions": "Partially cloudy",
          "icon": "partly-cloudy-night",
          "stations": null,
          "source": "fcst"
        },
        {
          "datetime": "06:00:00",
          "datetimeEpoch": 1765634400,
          "temp": 53.9,
          "feelslike": 53.9,
          "humidity": 84.13,
          "dew": 49.2,
          "precip": 0.0,
          "precipprob": 0.0,
          "snow": 0.0,
          "snowdepth": 0.0,
          "preciptype": null,
          "windgust": 4.5,
          "windspeed": 1.8,
          "winddir": 60.0,
          "pressure": 1015.0,
          "visibility": 15.0,
          "cloudcover": 50.0,
          "solarradiation": 0.0,
          "solarenergy": 0.0,
          "uvindex": 0.0,
          "severerisk": 10.0,
          "conditions": "Partially cloudy",
          "icon": "partly-cloudy-night",
          "stations": null,
          "source": "fcst"
        },
        {
          "datetime": "07:00:00",
          "datetimeEpoch": 1765638000,
          "temp": 53.7,
          "feelslike": 53.7,
          "humidity": 84.69,
          "dew": 49.2,
          "precip": 0.0,
          "precipprob": 0.0,
          "snow": 0.0,
          "snowdepth": 0.0,
          "preciptype": null,
          "windgust": 4.3,
          "windspeed": 1.8,
          "winddir": 60.0,
          "pressure": 1015.0,
          "visibility": 15.0,
          "cloudcover": 53.0,
          "solarradiation": 0.0,
          "solarenergy": 0.0,
          "uvindex": 0.0,
          "severerisk": 10.0,
          "conditions": "Partially cloudy",
          "icon": "partly-cloudy-day",
          "stations": null,
          "source": "fcst"
        },
        {
          "datetime": "08:00:00",
          "datetimeEpoch": 1765641600,
          "temp": 57.3,
          "feelslike": 57.3,
          "humidity": 77.36,
          "dew": 50.3,
          "precip": 0.0,
          "precipprob": 0.0,
          "snow": 0.0,
          "snowdepth": 0.0,
          "preciptype": null,
          "windgust": 4.3,
          "windspeed": 1.6,
          "winddir": 40.0,
          "pressure": 1015.0,
          "visibility": 15.0,
          "cloudcover": 47.7,
          "solarradiation": 35.0,
          "solarenergy": 0.1,
          "uvindex": 0.0,
          "severerisk": 10.0,
          "conditions": "Partially cloudy",
          "icon": "partly-cloudy-day",
          "stations": null,
          "source": "fcst"
        },
        {
          "datetime": "09:00:00",
          "datetimeEpoch": 1765645200,
          "temp": 60.9,
          "feelslike": 60.9,
          "humidity": 71.28,
          "dew": 51.5,
          "precip": 0.0,
          "precipprob": 0.0,
          "snow": 0.0,
          "snowdepth": 0.0,
          "preciptype": null,
          "windgust": 4.5,
          "windspeed": 1.1,
          "winddir": 20.0,
          "pressure": 1016.0,
          "visibility": 15.0,
          "cloudcover": 42.3,
          "solarradiation": 69.0,
          "solarenergy": 0.2,
          "uvindex": 1.0,
          "severerisk": 10.0,
          "conditions": "Partially cloudy",
          "icon": "partly-cloudy-day",
          "stations": null,
          "source": "fcst"
        },
        {
          "datetime": "10:00:00",
          "datetimeEpoch": 1765648800,
          "temp": 64.5,
          "feelslike": 64.5,
          "humidity": 65.34,
          "dew": 52.6,
          "precip": 0.0,
          "precipprob": 0.0,
          "snow": 0.0,
          "snowdepth": 0.0,
          "preciptype": null,
          "windgust": 4.5,
          "windspeed": 0.9,
          "winddir": 0.0,
          "pressure": 1016.0,
          "visibility": 15.0,
          "cloudcover": 37.0,
          "solarradiation": 104.0,
          "solarenergy": 0.4,
          "uvindex": 1.0,
          "severerisk": 10.0,
          "conditions": "Partially cloudy",
          "icon": "partly-cloudy-day",
          "stations": null,
          "source": "fcst"
        },
        {
          "datetime": "11:00:00",
          "datetimeEpoch": 1765652400,
          "temp": 66.8,
          "feelslike": 66.8,
          "humidity": 59.85,
          "dew": 52.4,
          "precip": 0.0,
          "precipprob": 0.0,
          "snow": 0.0,
          "snowdepth": 0.0,
          "preciptype": null,
          "windgust": 6.0,
          "windspeed": 1.8,
          "winddir": 80.0,
          "pressure": 1015.0,
          "visibility": 15.0,
          "cloudcover": 36.3,
          "solarradiation": 219.0,
          "solarenergy": 0.8,
          "uvindex": 2.0,
          "severerisk": 10.0,
          "conditions": "Partially cloudy",
          "icon": "partly-cloudy-day",
          "stations": null,
          "source": "fcst"
        },
        {
          "datetime": "12:00:00",
          "datetimeEpoch": 1765656000,
          "temp": 69.0,
          "feelslike": 69.0,
          "humidity": 55.19,
          "dew": 52.2,
          "precip": 0.0,
          "precipprob": 0.0,
          "snow": 0.0,
          "snowdepth": 0.0,
          "preciptype": null,
          "windgust": 7.6,
          "windspeed": 2.7,
          "winddir": 160.0,
          "pressure": 1015.0,
          "visibility": 15.0,
          "cloudcover": 35.7,
          "solarradiation": 333.0,
          "solarenergy": 1.2,
          "uvindex": 3.0,
          "severerisk": 10.0,
          "conditions": "Partially cloudy",
          "icon": "partly-cloudy-day",
          "stations": null,
          "source": "fcst"
        },
        {
          "datetime": "13:00:00",
          "datetimeEpoch": 1765659600,
          "temp": 71.3,
          "feelslike": 71.3,
          "humidity": 50.63,
          "dew": 52.1,
          "precip": 0.0,
          "precipprob": 0.0,
          "snow": 0.0,
          "snowdepth": 0.0,
          "preciptype": null,
          "windgust": 9.2,
          "windspeed": 3.6,
          "winddir": 240.0,
          "pressure": 1014.0,
          "visibility": 15.0,
          "cloudcover": 35.0,
          "solarradiation": 448.0,
          "solarenergy": 1.6,
          "uvindex": 4.0,
          "severerisk": 10.0,
          "conditions": "Partially cloudy",
          "icon": "partly-cloudy-day",
          "stations": null,
          "source": "fcst"
        },
        {
          "datetime": "14:00:00",
          "datetimeEpoch": 1765663200,
          "temp": 70.4,
          "feelslike": 70.4,
          "humidity": 53.24,
          "dew": 52.6,
          "precip": 0.0,
          "precipprob": 0.0,
          "snow": 0.0,
          "snowdepth": 0.0,
          "preciptype": null,
          "windgust": 9.2,
          "windspeed": 3.8,
          "winddir": 240.0,
          "pressure": 1014.0,
          "visibility": 15.0,
          "cloudcover": 32.0,
          "solarradiation": 424.0,
          "solarenergy": 1.5,
          "uvindex": 4.0,
          "severerisk": 10.0,
          "conditions": "Partially cloudy",
          "icon": "partly-cloudy-day",
          "stations": null,
          "source": "fcst"
        },
        {
          "datetime": "15:00:00",
          "datetimeEpoch": 1765666800,
          "temp": 69.3,
          "feelslike": 69.3,
          "humidity": 55.98,
          "dew": 53.0,
          "precip": 0.0,
          "precipprob": 0.0,
          "snow": 0.0,
          "snowdepth": 0.0,
          "preciptype": null,
          "windgust": 8.9,
          "windspeed": 4.3,
          "winddir": 240.0,
          "pressure": 1013.0,
          "visibility": 15.0,
          "cloudcover": 29.0,
          "solarradiation": 399.0,
          "solarenergy": 1.4,
          "uvindex": 4.0,
          "severerisk": 10.0,
          "conditions": "Partially cloudy",
          "icon": "partly-cloudy-day",
          "stations": null,
          "source": "fcst"
        },
        {
          "datetime": "16:00:00",
          "datetimeEpoch": 1765670400,
          "temp": 68.4,
          "feelslike": 68.4,
          "humidity": 58.89,
          "dew": 53.5,
          "precip": 0.0,
          "precipprob": 0.0,
          "snow": 0.0,
          "snowdepth": 0.0,
          "preciptype": null,
          "windgust": 8.9,
          "windspeed": 4.5,
          "winddir": 240.0,
          "pressure": 1013.0,
          "visibility": 15.0,
          "cloudcover": 26.0,
          "solarradiation": 375.0,
          "solarenergy": 1.3,
          "uvindex": 4.0,
          "severerisk": 10.0,
          "conditions": "Partially cloudy",
          "icon": "partly-cloudy-day",
          "stations": null,
          "source": "fcst"
        },
        {
          "datetime": "17:00:00",
          "datetimeEpoch": 1765674000,
          "temp": 65.7,
          "feelslike": 65.7,
          "humidity": 65.5,
          "dew": 53.9,
          "precip": 0.0,
          "precipprob": 0.0,
          "snow": 0.0,
          "snowdepth": 0.0,
          "preciptype": null,
          "windgust": 7.4,
          "windspeed": 3.6,
          "winddir": 236.7,
          "pressure": 1014.0,
          "visibility": 15.0,
          "cloudcover": 26.7,
          "solarradiation": 252.0,
          "solarenergy": 0.9,
          "uvindex": 0.0,
          "severerisk": 10.0,
          "conditions": "Partially cloudy",
          "icon": "partly-cloudy-night",
          "stations": null,
          "source": "fcst"
        },
        {
          "datetime": "18:00:00",
          "datetimeEpoch": 1765677600,
          "temp": 63.2,
          "feelslike": 63.2,
          "humidity": 71.99,
          "dew": 54.1,
          "precip": 0.0,
          "precipprob": 0.0,
          "snow": 0.0,
          "snowdepth": 0.0,
          "preciptype": null,
          "windgust": 6.0,
          "windspeed": 2.7,
          "winddir": 233.3,
          "pressure": 1014.0,
          "visibility": 15.0,
          "cloudcover": 27.3,
          "solarradiation": 129.0,
          "solarenergy": 0.5,
          "uvindex": 0.0,
          "severerisk": 10.0,
          "conditions": "Partially cloudy",
          "icon": "partly-cloudy-night",
          "stations": null,
          "source": "fcst"
        },
        {
          "datetime": "19:00:00",
          "datetimeEpoch": 1765681200,
          "temp": 60.5,
          "feelslike": 60.5,
          "humidity": 80.24,
          "dew": 54.4,
          "precip": 0.0,
          "precipprob": 0.0,
          "snow": 0.0,
          "snowdepth": 0.0,
          "preciptype": null,
          "windgust": 4.5,
          "windspeed": 1.8,
          "winddir": 230.0,
          "pressure": 1015.0,
          "visibility": 15.0,
          "cloudcover": 28.0,
          "solarradiation": 6.0,
          "solarenergy": 0.0,
          "uvindex": 0.0,
          "severerisk": 10.0,
          "conditions": "Partially cloudy",
          "icon": "partly-cloudy-night",
          "stations": null,
          "source": "fcst"
        },
        {
          "datetime": "20:00:00",
          "datetimeEpoch": 1765684800,
          "temp": 59.3,
          "feelslike": 59.3,
          "humidity": 82.82,
          "dew": 54.1,
          "precip": 0.0,
          "precipprob": 0.0,
          "snow": 0.0,
          "snowdepth": 0.0,
          "preciptype": null,
          "windgust": 4.7,
          "windspeed": 1.8,
          "winddir": 200.0,
          "pressure": 1015.0,
          "visibility": 15.0,
          "cloudcover": 30.3,
          "solarradiation": 5.0,
          "solarenergy": 0.0,
          "uvindex": 0.0,
          "severerisk": 10.0,
          "conditions": "Partially cloudy",
          "icon": "partly-cloudy-night",
          "stations": null,
          "source": "fcst"
        },
        {
          "datetime": "21:00:00",
          "datetimeEpoch": 1765688400,
          "temp": 57.8,
          "feelslike": 57.8,
          "humidity": 85.5,
          "dew": 53.5,
          "precip": 0.0,
          "precipprob": 0.0,
          "snow": 0.0,
          "snowdepth": 0.0,
          "preciptype": null,
          "windgust": 4.7,
          "windspeed": 1.8,
          "winddir": 170.0,
          "pressure": 1016.0,
          "visibility": 15.0,
          "cloudcover": 32.7,
          "solarradiation": 4.0,
          "solarenergy": 0.0,
          "uvindex": 0.0,
          "severerisk": 10.0,
          "conditions": "Partially cloudy",
          "icon": "partly-cloudy-night",
          "stations": null,
          "source": "fcst"
        },
        {
          "datetime": "22:00:00",
          "datetimeEpoch": 1765692000,
          "temp": 56.6,
          "feelslike": 56.6,
          "humidity": 88.3,
          "dew": 53.1,
          "precip": 0.0,
          "precipprob": 0.0,
          "snow": 0.0,
          "snowdepth": 0.0,
          "preciptype": null,
          "windgust": 4.9,
          "windspeed": 1.8,
          "winddir": 140.0,
          "pressure": 1016.0,
          "visibility": 15.0,
          "cloudcover": 35.0,
          "solarradiation": 3.0,
          "solarenergy": 0.0,
          "uvindex": 0.0,
          "severerisk": 10.0,
          "conditions": "Partially cloudy",
          "icon": "partly-cloudy-night",
          "stations": null,
          "source": "fcst"
        },
        {
          "datetime": "23:00:00",
          "datetimeEpoch": 1765695600,
          "temp": 56.0,
          "feelslike": 56.0,
          "humidity": 87.69,
          "dew": 52.4,
          "precip": 0.0,
          "precipprob": 0.0,
          "snow": 0.0,
          "snowdepth": 0.0,
          "preciptype": null,
          "windgust": 4.5,
          "windspeed": 1.8,
          "winddir": 113.3,
          "pressure": 1016.0,
          "visibility": 15.0,
          "cloudcover": 41.0,
          "solarradiation": 2.0,
          "solarenergy": 0.0,
          "uvindex": 0.0,
          "severerisk": 10.0,
          "conditions": "Partially cloudy",
          "icon": "partly-cloudy-night",
          "stations": null,
          "source": "fcst"
        }
      ]
    },
    {
      "datetime": "2025-12-14",
      "datetimeEpoch": 1765699200,
      "tempmax": 67.9,
      "tempmin": 53.0,
      "temp": 58.9,
      "feelslikemax": 67.9,
      "feelslikemin": 53.0,
      "feelslike": 58.9,
      "dew": 51.7,
      "humidity": 77.9,
      "precip": 0.0,
      "precipprob": 0.0,
      "precipcover": 0.0,
      "preciptype": null,
      "snow": 0.0,
      "snowdepth": 0.0,
      "windgust": 9.4,
      "windspeed": 4.5,
      "winddir": 250.3,
      "pressure": 1016.1,
      "cloudcover": 38.1,
      "visibility": 15.0,
      "solarradiation": 136.9,
      "solarenergy": 11.5,
      "uvindex": 5.0,
      "severerisk": 10.0,
      "sunrise": "06:49:21",
      "sunriseEpoch": 1765723761,
      "sunset": "16:44:17",
      "sunsetEpoch": 1765759457,
      "moonphase": 0.83,
      "conditions": "Partially cloudy",
      "description": "Partly cloudy throughout the day.",
      "icon": "partly-cloudy-day",
      "stations": null,
      "source": "fcst",
      "hours": [
        {
          "datetime": "00:00:00",
          "datetimeEpoch": 1765699200,
          "temp": 55.3,
          "feelslike": 55.3,
          "humidity": 88.24,
          "dew": 51.9,
          "precip": 0.0,
          "precipprob": 0.0,
          "snow": 0.0,
          "snowdepth": 0.0,
          "preciptype": null,
          "windgust": 4.0,
          "windspeed": 1.8,
          "winddir": 86.7,
          "pressure": 1015.0,
          "visibility": 15.0,
          "cloudcover": 47.0,
          "solarradiation": 1.0,
          "solarenergy": 0.0,
          "uvindex": 0.0,
          "severerisk": 10.0,
          "conditions": "Partially cloudy",
          "icon": "partly-cloudy-night",
          "stations": null,
          "source": "fcst"
        },
        {
          "datetime": "01:00:00",
          "datetimeEpoch": 1765702800,
          "temp": 54.8,
          "feelslike": 54.8,
          "humidity": 87.63,
          "dew": 51.2,
          "precip": 0.0,
          "precipprob": 0.0,
          "snow": 0.0,
          "snowdepth": 0.0,
          "preciptype": null,
          "windgust": 3.6,
          "windspeed": 1.8,
          "winddir": 60.0,
          "pressure": 1015.0,
          "visibility": 15.0,
          "cloudcover": 53.0,
          "solarradiation": 0.0,
          "solarenergy": 0.0,
          "uvindex": 0.0,
          "severerisk": 10.0,
          "conditions": "Partially cloudy",
          "icon": "partly-cloudy-night",
          "stations": null,
          "source": "fcst"
        },
        {
          "datetime": "02:00:00",
          "datetimeEpoch": 1765706400,
          "temp": 54.4,
          "feelslike": 54.4,
          "humidity": 87.61,
          "dew": 50.8,
          "precip": 0.0,
          "precipprob": 0.0,
          "snow": 0.0,
          "snowdepth": 0.0,
          "preciptype": null,
          "windgust": 3.8,
          "windspeed": 1.8,
          "winddir": 56.7,
          "pressure": 1015.0,
          "visibility": 15.0,
          "cloudcover": 56.3,
          "solarradiation": 0.0,
          "solarenergy": 0.0,
          "uvindex": 0.0,
          "severerisk": 10.0,
          "conditions": "Partially cloudy",
          "icon": "partly-cloudy-night",
          "stations": null,
          "source": "fcst"
        },
        {
          "datetime": "03:00:00",
          "datetimeEpoch": 1765710000,
          "temp": 53.9,
          "feelslike": 53.9,
          "humidity": 87.58,
          "dew": 50.3,
          "precip": 0.0,
          "precipprob": 0.0,
          "snow": 0.0,
          "snowdepth": 0.0,
          "preciptype": null,
          "windgust": 4.3,
          "windspeed": 1.8,
          "winddir": 53.3,
          "pressure": 1015.0,
          "visibility": 15.0,
          "cloudcover": 59.7,
          "solarradiation": 0.0,
          "solarenergy": 0.0,
          "uvindex": 0.0,
          "severerisk": 10.0,
          "conditions": "Partially cloudy",
          "icon": "partly-cloudy-night",
          "stations": null,
          "source": "fcst"
        },
        {
          "datetime": "04:00:00",
          "datetimeEpoch": 1765713600,
          "temp": 53.5,
          "feelslike": 53.5,
          "humidity": 87.56,
          "dew": 49.9,
          "precip": 0.0,
          "precipprob": 0.0,
          "snow": 0.0,
          "snowdepth": 0.0,
          "preciptype": null,
          "windgust": 4.5,
          "windspeed": 1.8,
          "winddir": 50.0,
          "pressure": 1015.0,
          "visibility": 15.0,
          "cloudcover": 63.0,
          "solarradiation": 0.0,
          "solarenergy": 0.0,
          "uvindex": 0.0,
          "severerisk": 10.0,
          "conditions": "Partially cloudy",
          "icon": "partly-cloudy-night",
          "stations": null,
          "source": "fcst"
        },
        {
          "datetime": "05:00:00",
          "datetimeEpoch": 1765717200,
          "temp": 53.3,
          "feelslike": 53.3,
          "humidity": 88.14,
          "dew": 49.9,
          "precip": 0.0,
          "precipprob": 0.0,
          "snow": 0.0,
          "snowdepth": 0.0,
          "preciptype": null,
          "windgust": 4.3,
          "windspeed": 1.8,
          "winddir": 43.3,
          "pressure": 1015.0,
          "visibility": 15.0,
          "cloudcover": 61.7,
          "solarradiation": 0.0,
          "solarenergy": 0.0,
          "uvindex": 0.0,
          "severerisk": 10.0,
          "conditions": "Partially cloudy",
          "icon": "partly-cloudy-night",
          "stations": null,
          "source": "fcst"
        },
        {
          "datetime": "06:00:00",
          "datetimeEpoch": 1765720800,
          "temp": 53.1,
          "feelslike": 53.1,
          "humidity": 88.13,
          "dew": 49.7,
          "precip": 0.0,
          "precipprob": 0.0,
          "snow": 0.0,
          "snowdepth": 0.0,
          "preciptype": null,
          "windgust": 4.3,
          "windspeed": 1.8,
          "winddir": 36.7,
          "pressure": 1016.0,
          "visibility": 15.0,
          "cloudcover": 60.3,
          "solarradiation": 0.0,
          "solarenergy": 0.0,
          "uvindex": 0.0,
          "severerisk": 10.0,
          "conditions": "Partially cloudy",
          "icon": "partly-cloudy-night",
          "stations": null,
          "source": "fcst"
        },
        {
          "datetime": "07:00:00",
          "datetimeEpoch": 1765724400,
          "temp": 53.0,
          "feelslike": 53.0,
          "humidity": 88.72,
          "dew": 49.7,
          "precip": 0.0,
          "precipprob": 0.0,
          "snow": 0.0,
          "snowdepth": 0.0,
          "preciptype": null,
          "windgust": 4.0,
          "windspeed": 1.8,
          "winddir": 30.0,
          "pressure": 1016.0,
          "visibility": 15.0,
          "cloudcover": 59.0,
          "solarradiation": 0.0,
          "solarenergy": 0.0,
          "uvindex": 0.0,
          "severerisk": 10.0,
          "conditions": "Partially cloudy",
          "icon": "partly-cloudy-day",
          "stations": null,
          "source": "fcst"
        },
        {
          "datetime": "08:00:00",
          "datetimeEpoch": 1765728000,
          "temp": 55.8,
          "feelslike": 55.8,
          "humidity": 82.04,
          "dew": 50.4,
          "precip": 0.0,
          "precipprob": 0.0,
          "snow": 0.0,
          "snowdepth": 0.0,
          "preciptype": null,
          "windgust": 4.3,
          "windspeed": 1.8,
          "winddir": 110.0,
          "pressure": 1017.0,
          "visibility": 15.0,
          "cloudcover": 52.0,
          "solarradiation": 41.0,
          "solarenergy": 0.1,
          "uvindex": 0.0,
          "severerisk": 10.0,
          "conditions": "Partially cloudy",
          "icon": "partly-cloudy-day",
          "stations": null,
          "source": "fcst"
        },
        {
          "datetime": "09:00:00",
          "datetimeEpoch": 1765731600,
          "temp": 58.7,
          "feelslike": 58.7,
          "humidity": 75.96,
          "dew": 51.2,
          "precip": 0.0,
          "precipprob": 0.0,
          "snow": 0.0,
          "snowdepth": 0.0,
          "preciptype": null,
          "windgust": 4.3,
          "windspeed": 1.8,
          "winddir": 190.0,
          "pressure": 1017.0,
          "visibility": 15.0,
          "cloudcover": 45.0,
          "solarradiation": 82.0,
          "solarenergy": 0.3,
          "uvindex": 1.0,
          "severerisk": 10.0,
          "conditions": "Partially cloudy",
          "icon": "partly-cloudy-day",
          "stations": null,
          "source": "fcst"
        },
        {
          "datetime": "10:00:00",
          "datetimeEpoch": 1765735200,
          "temp": 61.6,
          "feelslike": 61.6,
          "humidity": 70.41,
          "dew": 51.9,
          "precip": 0.0,
          "precipprob": 0.0,
          "snow": 0.0,
          "snowdepth": 0.0,
          "preciptype": null,
          "windgust": 4.5,
          "windspeed": 1.8,
          "winddir": 270.0,
          "pressure": 1018.0,
          "visibility": 15.0,
          "cloudcover": 38.0,
          "solarradiation": 123.0,
          "solarenergy": 0.4,
          "uvindex": 1.0,
          "severerisk": 10.0,
          "conditions": "Partially cloudy",
          "icon": "partly-cloudy-day",
          "stations": null,
          "source": "fcst"
        },
        {
          "datetime": "11:00:00",
          "datetimeEpoch": 1765738800,
          "temp": 63.8,
          "feelslike": 63.8,
          "humidity": 65.26,
          "dew": 51.9,
          "precip": 0.0,
          "precipprob": 0.0,
          "snow": 0.0,
          "snowdepth": 0.0,
          "preciptype": null,
          "windgust": 6.0,
          "windspeed": 2.5,
          "winddir": 263.3,
          "pressure": 1017.0,
          "visibility": 15.0,
          "cloudcover": 33.3,
          "solarradiation": 262.0,
          "solarenergy": 0.9,
          "uvindex": 3.0,
          "severerisk": 10.0,
          "conditions": "Partially cloudy",
          "icon": "partly-cloudy-day",
          "stations": null,
          "source": "fcst"
        },
        {
          "datetime": "12:00:00",
          "datetimeEpoch": 1765742400,
          "temp": 65.7,
          "feelslike": 65.7,
          "humidity": 60.9,
          "dew": 51.9,
          "precip": 0.0,
          "precipprob": 0.0,
          "snow": 0.0,
          "snowdepth": 0.0,
          "preciptype": null,
          "windgust": 7.6,
          "windspeed": 3.1,
          "winddir": 256.7,
          "pressure": 1016.0,
          "visibility": 15.0,
          "cloudcover": 28.7,
          "solarradiation": 400.0,
          "solarenergy": 1.4,
          "uvindex": 4.0,
          "severerisk": 10.0,
          "conditions": "Partially cloudy",
          "icon": "partly-cloudy-day",
          "stations": null,
          "source": "fcst"
        },
        {
          "datetime": "13:00:00",
          "datetimeEpoch": 1765746000,
          "temp": 67.9,
          "feelslike": 67.9,
          "humidity": 56.52,
          "dew": 51.9,
          "precip": 0.0,
          "precipprob": 0.0,
          "snow": 0.0,
          "snowdepth": 0.0,
          "preciptype": null,
          "windgust": 9.2,
          "windspeed": 3.8,
          "winddir": 250.0,
          "pressure": 1015.0,
          "visibility": 15.0,
          "cloudcover": 24.0,
          "solarradiation": 539.0,
          "solarenergy": 1.9,
          "uvindex": 5.0,
          "severerisk": 10.0,
          "conditions": "Partially cloudy",
          "icon": "partly-cloudy-day",
          "stations": null,
          "source": "fcst"
        },
        {
          "datetime": "14:00:00",
          "datetimeEpoch": 1765749600,
          "temp": 67.4,
          "feelslike": 67.4,
          "humidity": 58.74,
          "dew": 52.4,
          "precip": 0.0,
          "precipprob": 0.0,
          "snow": 0.0,
          "snowdepth": 0.0,
          "preciptype": null,
          "windgust": 9.2,
          "windspeed": 4.0,
          "winddir": 246.7,
          "pressure": 1015.0,
          "visibility": 15.0,
          "cloudcover": 21.7,
          "solarradiation": 500.0,
          "solarenergy": 1.8,
          "uvindex": 5.0,
          "severerisk": 10.0,
          "conditions": "Partially cloudy",
          "icon": "partly-cloudy-day",
          "stations": null,
          "source": "fcst"
        },
        {
          "datetime": "15:00:00",
          "datetimeEpoch": 1765753200,
          "temp": 66.6,
          "feelslike": 66.6,
          "humidity": 61.43,
          "dew": 53.0,
          "precip": 0.0,
          "precipprob": 0.0,
          "snow": 0.0,
          "snowdepth": 0.0,
          "preciptype": null,
          "windgust": 9.4,
          "windspeed": 4.3,
          "winddir": 243.3,
          "pressure": 1015.0,
          "visibility": 15.0,
          "cloudcover": 19.3,
          "solarradiation": 461.0,
          "solarenergy": 1.7,
          "uvindex": 5.0,
          "severerisk": 10.0,
          "conditions": "Clear",
          "icon": "clear-day",
          "stations": null,
          "source": "fcst"
        },
        {
          "datetime": "16:00:00",
          "datetimeEpoch": 1765756800,
          "temp": 66.1,
          "feelslike": 66.1,
          "humidity": 63.84,
          "dew": 53.5,
          "precip": 0.0,
          "precipprob": 0.0,
          "snow": 0.0,
          "snowdepth": 0.0,
          "preciptype": null,
          "windgust": 9.4,
          "windspeed": 4.5,
          "winddir": 240.0,
          "pressure": 1015.0,
          "visibility": 15.0,
          "cloudcover": 17.0,
          "solarradiation": 422.0,
          "solarenergy": 1.5,
          "uvindex": 4.0,
          "severerisk": 10.0,
          "conditions": "Clear",
          "icon": "clear-day",
          "stations": null,
          "source": "fcst"
        },
        {
          "datetime": "17:00:00",
          "datetimeEpoch": 1765760400,
          "temp": 63.6,
          "feelslike": 63.6,
          "humidity": 69.7,
          "dew": 53.5,
          "precip": 0.0,
          "precipprob": 0.0,
          "snow": 0.0,
          "snowdepth": 0.0,
          "preciptype": null,
          "windgust": 7.8,
          "windspeed": 3.6,
          "winddir": 246.7,
          "pressure": 1016.0,
          "visibility": 15.0,
          "cloudcover": 17.7,
          "solarradiation": 284.0,
          "solarenergy": 1.0,
          "uvindex": 0.0,
          "severerisk": 10.0,
          "conditions": "Clear",
          "icon": "clear-night",
          "stations": null,
          "source": "fcst"
        },
        {
          "datetime": "18:00:00",
          "datetimeEpoch": 1765764000,
          "temp": 61.2,
          "feelslike": 61.2,
          "humidity": 76.19,
          "dew": 53.7,
          "precip": 0.0,
          "precipprob": 0.0,
          "snow": 0.0,
          "snowdepth": 0.0,
          "preciptype": null,
          "windgust": 6.0,
          "windspeed": 2.7,
          "winddir": 253.3,
          "pressure": 1016.0,
          "visibility": 15.0,
          "cloudcover": 18.3,
          "solarradiation": 145.0,
          "solarenergy": 0.5,
          "uvindex": 0.0,
          "severerisk": 10.0,
          "conditions": "Clear",
          "icon": "clear-night",
          "stations": null,
          "source": "fcst"
        },
        {
          "datetime": "19:00:00",
          "datetimeEpoch": 1765767600,
          "temp": 58.7,
          "feelslike": 58.7,
          "humidity": 83.33,
          "dew": 53.7,
          "precip": 0.0,
          "precipprob": 0.0,
          "snow": 0.0,
          "snowdepth": 0.0,
          "preciptype": null,
          "windgust": 4.5,
          "windspeed": 1.8,
          "winddir": 260.0,
          "pressure": 1017.0,
          "visibility": 15.0,
          "cloudcover": 19.0,
          "solarradiation": 7.0,
          "solarenergy": 0.0,
          "uvindex": 0.0,
          "severerisk": 10.0,
          "conditions": "Clear",
          "icon": "clear-night",
          "stations": null,
          "source": "fcst"
        },
        {
          "datetime": "20:00:00",
          "datetimeEpoch": 1765771200,
          "temp": 57.6,
          "feelslike": 57.6,
          "humidity": 84.37,
          "dew": 53.0,
          "precip": 0.0,
          "precipprob": 0.0,
          "snow": 0.0,
          "snowdepth": 0.0,
          "preciptype": null,
          "windgust": 4.5,
          "windspeed": 1.8,
          "winddir": 190.0,
          "pressure": 1017.0,
          "visibility": 15.0,
          "cloudcover": 23.3,
          "solarradiation": 6.0,
          "solarenergy": 0.0,
          "uvindex": 0.0,
          "severerisk": 10.0,
          "conditions": "Partially cloudy",
          "icon": "partly-cloudy-night",
          "stations": null,
          "source": "fcst"
        },
        {
          "datetime": "21:00:00",
          "datetimeEpoch": 1765774800,
          "temp": 56.6,
          "feelslike": 56.6,
          "humidity": 85.43,
          "dew": 52.2,
          "precip": 0.0,
          "precipprob": 0.0,
          "snow": 0.0,
          "snowdepth": 0.0,
          "preciptype": null,
          "windgust": 4.5,
          "windspeed": 1.8,
          "winddir": 120.0,
          "pressure": 1018.0,
          "visibility": 15.0,
          "cloudcover": 27.7,
          "solarradiation": 5.0,
          "solarenergy": 0.0,
          "uvindex": 0.0,
          "severerisk": 10.0,
          "conditions": "Partially cloudy",
          "icon": "partly-cloudy-night",
          "stations": null,
          "source": "fcst"
        },
        {
          "datetime": "22:00:00",
          "datetimeEpoch": 1765778400,
          "temp": 55.5,
          "feelslike": 55.5,
          "humidity": 86.51,
          "dew": 51.5,
          "precip": 0.0,
          "precipprob": 0.0,
          "snow": 0.0,
          "snowdepth": 0.0,
          "preciptype": null,
          "windgust": 4.5,
          "windspeed": 1.8,
          "winddir": 50.0,
          "pressure": 1018.0,
          "visibility": 15.0,
          "cloudcover": 32.0,
          "solarradiation": 4.0,
          "solarenergy": 0.0,
          "uvindex": 0.0,
          "severerisk": 10.0,
          "conditions": "Partially cloudy",
          "icon": "partly-cloudy-night",
          "stations": null,
          "source": "fcst"
        },
        {
          "datetime": "23:00:00",
          "datetimeEpoch": 1765782000,
          "temp": 54.9,
          "feelslike": 54.9,
          "humidity": 86.48,
          "dew": 51.0,
          "precip": 0.0,
          "precipprob": 0.0,
          "snow": 0.0,
          "snowdepth": 0.0,
          "preciptype": null,
          "windgust": 4.5,
          "windspeed": 1.8,
          "winddir": 53.3,
          "pressure": 1018.0,
          "visibility": 15.0,
          "cloudcover": 36.7,
          "solarradiation": 3.0,
          "solarenergy": 0.0,
          "uvindex": 0.0,
          "severerisk": 10.0,
          "conditions": "Partially cloudy",
          "icon": "partly-cloudy-night",
          "stations": null,
          "source": "fcst"
        }
      ]
    }
  ],
  "alerts": []
}